L8_reflectance/L8_reflectance.py
L8_reflectance/L8_utils.py
L8_reflectance-0.0.5.dist-info/METADATA
L8_reflectance-0.0.5.dist-info/WHEEL
L8_reflectance-0.0.5.dist-info/dependency_links.txt
L8_reflectance-0.0.5.dist-info/entry_points.txt
L8_reflectance-0.0.5.dist-info/top_level.txt
L8_reflectance-0.0.5.dist-info/RECORD
